README.md
pyproject.toml
setup.py
dyn_libs_test.egg-info/PKG-INFO
dyn_libs_test.egg-info/SOURCES.txt
dyn_libs_test.egg-info/dependency_links.txt
dyn_libs_test.egg-info/namespace_packages.txt
dyn_libs_test.egg-info/requires.txt
dyn_libs_test.egg-info/top_level.txt
mobio/libs/__init__.py
mobio/libs/dynamic_field/__init__.py
mobio/libs/dynamic_field/common/__init__.py
mobio/libs/dynamic_field/common/es_paginate.py
mobio/libs/dynamic_field/common/utils.py
mobio/libs/dynamic_field/controllers/__init__.py
mobio/libs/dynamic_field/controllers/i_base_dyn_controller.py
mobio/libs/dynamic_field/controllers/i_base_filter_controller.py
mobio/libs/dynamic_field/helpers/__init__.py
mobio/libs/dynamic_field/helpers/field_helper/__init__.py
mobio/libs/dynamic_field/helpers/field_helper/base_field.py
mobio/libs/dynamic_field/helpers/field_helper/i_base_config.py
mobio/libs/dynamic_field/models/__init__.py
mobio/libs/dynamic_field/models/elastic/__init__.py
mobio/libs/dynamic_field/models/elastic/base_model.py
mobio/libs/dynamic_field/models/mongo/__init__.py
mobio/libs/dynamic_field/models/mongo/base_model.py
mobio/libs/dynamic_field/models/mongo/db_manager.py
mobio/libs/dynamic_field/models/mongo/field_history_model.py
mobio/libs/dynamic_field/models/mongo/merchant_base_fields.py
mobio/libs/dynamic_field/models/mongo/merchant_config.py
mobio/libs/dynamic_field/models/mongo/staff_display_fields.py